normas/__init__.py
normas/diretriz.py
diretriz_vigilancia-0.0.2.dist-info/LICENSE
diretriz_vigilancia-0.0.2.dist-info/METADATA
diretriz_vigilancia-0.0.2.dist-info/WHEEL
diretriz_vigilancia-0.0.2.dist-info/top_level.txt
diretriz_vigilancia-0.0.2.dist-info/RECORD
